clld_corpus_plugin/__init__.py
clld_corpus_plugin/datatables.py
clld_corpus_plugin/interfaces.py
clld_corpus_plugin/models.py
clld_corpus_plugin/util.py
clld_corpus_plugin/cldf/SpeakerTable-metadata.json
clld_corpus_plugin/cldf/TextTable-metadata.json
clld_corpus_plugin/cldf/__init__.py
clld_corpus_plugin/static/clld-corpus.css
clld_corpus_plugin/static/clld-corpus.js
clld_corpus_plugin/templates/meaning/detail_html.mako
clld_corpus_plugin/templates/meaning/index_html.mako
clld_corpus_plugin/templates/sentence/detail_html.mako
clld_corpus_plugin/templates/speaker/detail_html.mako
clld_corpus_plugin/templates/speaker/index_html.mako
clld_corpus_plugin/templates/tag/detail_html.mako
clld_corpus_plugin/templates/tag/index_html.mako
clld_corpus_plugin/templates/text/detail_html.mako
clld_corpus_plugin/templates/text/index_html.mako
clld_corpus_plugin/templates/wordform/detail_html.mako
clld_corpus_plugin/templates/wordform/index_html.mako
clld_corpus_plugin-0.0.8.dist-info/LICENSE
clld_corpus_plugin-0.0.8.dist-info/METADATA
clld_corpus_plugin-0.0.8.dist-info/WHEEL
clld_corpus_plugin-0.0.8.dist-info/top_level.txt
clld_corpus_plugin-0.0.8.dist-info/RECORD
